sqlalchemy_altibase7/__init__.py
sqlalchemy_altibase7/base.py
sqlalchemy_altibase7/pyodbc.py
sqlalchemy_altibase7/requirements.py
sqlalchemy_altibase7-0.0.6.dist-info/METADATA
sqlalchemy_altibase7-0.0.6.dist-info/WHEEL
sqlalchemy_altibase7-0.0.6.dist-info/entry_points.txt
sqlalchemy_altibase7-0.0.6.dist-info/top_level.txt
sqlalchemy_altibase7-0.0.6.dist-info/RECORD
