Metadata-Version: 2.4
Name: sqlalchemy_altibase7
Version: 0.0.6
Summary: Altibase for SQLAlchemy
Author-email: Hess Lee <hess.lee7@gmail.com>
License: MIT
Project-URL: Source Code, https://github.com/hesslee/sqlalchemy-altibase7
Keywords: SQLAlchemy Altibase
Classifier: Development Status :: 3 - Alpha
Classifier: Intended Audience :: Developers
Classifier: License :: OSI Approved :: MIT License
Classifier: Programming Language :: Python :: 3
Classifier: Topic :: Database :: Front-Ends
Classifier: Operating System :: OS Independent
Requires-Dist: odbcinst
Requires-Dist: pyodbc
Requires-Dist: sqlalchemy>=1.3.24
Provides-Extra: lint
Requires-Dist: black; extra == "lint"
Requires-Dist: flake8; extra == "lint"
Requires-Dist: mypy; extra == "lint"
Requires-Dist: isort; extra == "lint"
Requires-Dist: pre-commit; extra == "lint"
Provides-Extra: test
Requires-Dist: pytest; extra == "test"
Requires-Dist: pytest-cov[all]; extra == "test"
